jhora/README.md
jhora/README_Package_Structure.md
jhora/__init__.py
jhora/_package_info.py
jhora/const.py
jhora/requirements.txt
jhora/setup.py
jhora/utils.py
jhora/data/all_nak_pad_boy_girl.csv
jhora/data/all_nak_pad_boy_girl_south.csv
jhora/data/hindu_festivals_multilingual_unicode_bom - Copy.csv
jhora/data/hindu_festivals_multilingual_unicode_bom.csv
jhora/data/pancha_pakshi_db.csv
jhora/data/program_inputs.txt
jhora/data/uscities.csv
jhora/data/world_cities_db.csv
jhora/data/world_cities_with_tz.csv
jhora/data/world_cities_with_tz_old.csv
jhora/data/ephe/ast_list.txt
jhora/data/ephe/seasnam.txt
jhora/data/ephe/sefstars.txt
jhora/data/ephe/seleapsec.txt
jhora/data/ephe/seorbel.txt
jhora/horoscope/README.md
jhora/horoscope/__init__.py
jhora/horoscope/main.py
jhora/horoscope/chart/README.md
jhora/horoscope/chart/__init__.py
jhora/horoscope/chart/arudhas.py
jhora/horoscope/chart/ashtakavarga.py
jhora/horoscope/chart/charts.py
jhora/horoscope/chart/dosha.py
jhora/horoscope/chart/house.py
jhora/horoscope/chart/raja_yoga.py
jhora/horoscope/chart/sphuta.py
jhora/horoscope/chart/strength.py
jhora/horoscope/chart/yoga.py
jhora/horoscope/dhasa/README.md
jhora/horoscope/dhasa/__init__.py
jhora/horoscope/dhasa/sudharsana_chakra.py
jhora/horoscope/dhasa/annual/mudda.py
jhora/horoscope/dhasa/annual/patyayini.py
jhora/horoscope/dhasa/graha/aayu.py
jhora/horoscope/dhasa/graha/applicability.py
jhora/horoscope/dhasa/graha/ashtottari.py
jhora/horoscope/dhasa/graha/buddhi_gathi.py
jhora/horoscope/dhasa/graha/chathuraaseethi_sama.py
jhora/horoscope/dhasa/graha/dwadasottari.py
jhora/horoscope/dhasa/graha/dwisatpathi.py
jhora/horoscope/dhasa/graha/kaala.py
jhora/horoscope/dhasa/graha/karaka.py
jhora/horoscope/dhasa/graha/karana_chathuraaseethi_sama.py
jhora/horoscope/dhasa/graha/naisargika.py
jhora/horoscope/dhasa/graha/panchottari.py
jhora/horoscope/dhasa/graha/saptharishi_nakshathra.py
jhora/horoscope/dhasa/graha/sataatbika.py
jhora/horoscope/dhasa/graha/shastihayani.py
pyjhora-4.5.5.dist-info/licenses/LICENSE
pyjhora-4.5.5.dist-info/METADATA
pyjhora-4.5.5.dist-info/WHEEL
pyjhora-4.5.5.dist-info/top_level.txt
pyjhora-4.5.5.dist-info/RECORD
