Metadata-Version: 2.4
Name: PyJHora
Version: 4.5.5
Summary: Complete Vedic Astrology Python package.
Author-email: Sundar Sundaresan <carnaticmusicguru2015@comcast.net>
License:  GNU AFFERO GENERAL PUBLIC LICENSE
Project-URL: homepage, https://github.com/naturalstupid/pyjhora
Project-URL: repository, https://github.com/naturalstupid/pyjhora
Project-URL: Issues, https://github.com/naturalstupid/pyjhora/issues
Keywords: Vedic Astrology,Astrology,Hindu Astrology,Kundali,Panchang,Horoscope,Hora,JHora
Classifier: Programming Language :: Python :: 3
Classifier: License :: OSI Approved :: MIT License
Classifier: Operating System :: OS Independent
Classifier: Intended Audience :: Other Audience
Classifier: Topic :: Scientific/Engineering :: Astronomy
Requires-Python: >=3.8
License-File: LICENSE
Dynamic: license-file
